notebookManagerPackageNX/__init__.py
notebookManagerPackageNX/notebook_manager.py
notebookManagerPackageNX-0.5.dist-info/METADATA
notebookManagerPackageNX-0.5.dist-info/WHEEL
notebookManagerPackageNX-0.5.dist-info/top_level.txt
notebookManagerPackageNX-0.5.dist-info/RECORD
